supercollect/__init__.py
supercollect/management/__init__.py
supercollect/management/commands/__init__.py
supercollect/management/commands/collectstatic.py
supercollect/utils.py
supercollect-1.1.1.dist-info/LICENSE
supercollect-1.1.1.dist-info/METADATA
supercollect-1.1.1.dist-info/WHEEL
supercollect-1.1.1.dist-info/RECORD
