Metadata-Version: 2.1
Name: supercollect
Version: 1.1.1
Summary: Supercharge collectstatic for remote storages
Author: mdd
Author-email: martin.diehl@terreon.de
Requires-Python: >=3.11
Classifier: Programming Language :: Python :: 3
Classifier: Programming Language :: Python :: 3.11
Classifier: Programming Language :: Python :: 3.12
Requires-Dist: django (>=4.2)
